<?xml version="1.0" encoding="UTF-8"?>
<knimeNode icon="./default.png" type="Source" xmlns="http://knime.org/node/v2.8" xmlns:xsi="http://www.w3.org/2001/XMLSchema-instance" xsi:schemaLocation="http://knime.org/node/v2.10 http://knime.org/node/v2.10.xsd">
    <name>Twitter Trends</name>
    
    <shortDescription>
        Returns Twitter Trends data via Twitter API
    </shortDescription>
    
    <fullDescription>
        <intro>This node uses Twitter API Connector to connect to Twitter API to pull Trends data.  It will first make a call to trends/available to download a list of available cities/countries and populated a the Place drop down.  Select a Country/City and it will then make a call to trends/place to pull down Twitter Trends data for that specifc city or country.</intro>
                
        <option name="Country">This is a drop down of available countries with Twitter Trends data.  This list is updated on the fly.</option>
        <option name="City">This is a drop down of available cities with Twitter Trends data.  This list is updated on the fly.</option>
    </fullDescription>
    
    <ports>
        <inPort index="0" name="Twitter API Connection">Twitter API Connection node</inPort>
        <outPort index="0" name="Twitter Trends Data">Twitter Trends data in table form</outPort>
    </ports>    
</knimeNode>
